rsdos-0.1.0.dist-info/METADATA
rsdos-0.1.0.dist-info/WHEEL
rsdos/__init__.py
rsdos/rsdos.abi3.so
rsdos-0.1.0.dist-info/RECORD
